fume/__init__.py
fume/cli/__init__.py
fume/cli/app.py
fume/cli/cg_commands.py
fume/cli/stream_commands.py
fume/grpc.py
yellowstone_api/__init__.py
yellowstone_api/fumarole_pb2.py
yellowstone_api/fumarole_pb2.pyi
yellowstone_api/fumarole_pb2_grpc.py
yellowstone_api/geyser_pb2.py
yellowstone_api/geyser_pb2.pyi
yellowstone_api/geyser_pb2_grpc.py
yellowstone_api/solana_storage_pb2.py
yellowstone_api/solana_storage_pb2.pyi
yellowstone_api/solana_storage_pb2_grpc.py
yellowstone_fume-0.2.0.dist-info/METADATA
yellowstone_fume-0.2.0.dist-info/WHEEL
yellowstone_fume-0.2.0.dist-info/entry_points.txt
yellowstone_fume-0.2.0.dist-info/RECORD
