Metadata-Version: 2.1
Name: yellowstone-fume
Version: 0.2.0
Summary: Yellowstone Fumarole CLI tool
Home-page: https://github.com/rpcpool/yellowstone-fumarole
Author: Louis-Vincent
Author-email: louis-vincent@triton.one
Requires-Python: >=3.10,<4.0
Classifier: Programming Language :: Python :: 3
Classifier: Programming Language :: Python :: 3.10
Classifier: Programming Language :: Python :: 3.11
Classifier: Programming Language :: Python :: 3.12
Classifier: Programming Language :: Python :: 3.13
Requires-Dist: base58 (>=2.1.1,<3.0.0)
Requires-Dist: click (>=8.1.7,<9.0.0)
Requires-Dist: grpcio (>=1.68.1,<2.0.0)
Requires-Dist: protobuf (>=5.29.1,<6.0.0)
Requires-Dist: tabulate (>=0.9.0,<0.10.0)
Requires-Dist: toml (>=0.10.2,<0.11.0)
Project-URL: Repository, https://github.com/rpcpool/yellowstone-fumarole
